firecrawl/__init__.py
firecrawl/client.py
firecrawl/exceptions.py
firecrawl/models.py
firecrawl/py.typed
firecrawl/utils.py
firecrawl_wb-0.2.0.dist-info/METADATA
firecrawl_wb-0.2.0.dist-info/WHEEL
firecrawl_wb-0.2.0.dist-info/licenses/LICENSE
firecrawl_wb-0.2.0.dist-info/RECORD
