Metadata-Version: 2.4
Name: firecrawl-wb
Version: 0.2.0
Summary: Lightweight, async-first Python wrapper for the Firecrawl v2 API
Project-URL: Homepage, https://github.com/wb200/firecrawl-wb
Project-URL: Documentation, https://github.com/wb200/firecrawl-wb#readme
Project-URL: Repository, https://github.com/wb200/firecrawl-wb
Project-URL: Issues, https://github.com/wb200/firecrawl-wb/issues
Author: wb200
License-Expression: MIT
License-File: LICENSE
Keywords: api-client,async,crawler,firecrawl,sitemap,web-extraction,web-scraping
Classifier: Development Status :: 4 - Beta
Classifier: Framework :: AsyncIO
Classifier: Intended Audience :: Developers
Classifier: License :: OSI Approved :: MIT License
Classifier: Operating System :: OS Independent
Classifier: Programming Language :: Python :: 3
Classifier: Programming Language :: Python :: 3.11
Classifier: Programming Language :: Python :: 3.12
Classifier: Programming Language :: Python :: 3.13
Classifier: Topic :: Internet :: WWW/HTTP
Classifier: Topic :: Software Development :: Libraries :: Python Modules
Classifier: Typing :: Typed
Requires-Python: >=3.11
Requires-Dist: httpx>=0.27.0
Requires-Dist: pydantic>=2.0.0
Provides-Extra: dev
Requires-Dist: mypy>=1.0; extra == 'dev'
Requires-Dist: pytest-asyncio>=0.23; extra == 'dev'
Requires-Dist: pytest>=8.0; extra == 'dev'
Requires-Dist: ruff>=0.8; extra == 'dev'
